github_emails/__init__.py
github_emails/access_limit.py
github_emails/commands.py
github_emails/config.py
github_emails/github_api.py
github_emails-0.0.6.dist-info/LICENSE
github_emails-0.0.6.dist-info/METADATA
github_emails-0.0.6.dist-info/WHEEL
github_emails-0.0.6.dist-info/entry_points.txt
github_emails-0.0.6.dist-info/top_level.txt
github_emails-0.0.6.dist-info/RECORD
