Metadata-Version: 2.1
Name: github-emails
Version: 0.0.6
Summary: 📫 A tool to get email addresses by action types such as `starred`, `watching` or `fork` on GitHub repositories
Home-page: https://github.com/wj-Mcat/github-emails
Author: wj-Mcat
Author-email: wjmcater@gmail.com
License: Apache-2.0
Platform: UNKNOWN
Classifier: Programming Language :: Python :: 3.8
Classifier: License :: OSI Approved :: Apache Software License
Classifier: Operating System :: OS Independent
Requires-Dist: wechaty-puppet
Requires-Dist: betterproto
Requires-Dist: chatie-grpc
